excelsior/__init__.py
excelsior/excelsior.cpython-313-x86_64-linux-gnu.so
excelsior/excelsior.pyi
excelsior_fast-0.11.3.dist-info/METADATA
excelsior_fast-0.11.3.dist-info/WHEEL
excelsior_fast-0.11.3.dist-info/licenses/LICENSE
excelsior_fast-0.11.3.dist-info/RECORD
