Metadata-Version: 2.4
Name: excelsior-fast
Version: 0.11.3
Classifier: Programming Language :: Python :: 3 :: Only
Classifier: Programming Language :: Rust
Classifier: License :: OSI Approved :: GNU General Public License v3 or later (GPLv3+)
Classifier: Operating System :: OS Independent
Requires-Dist: numpy>=2.2.6
Requires-Dist: openpyxl>=3.1.5
Requires-Dist: pip>=25.3
Requires-Dist: polars==1.35.*
Requires-Dist: pyarrow>=20
License-File: LICENSE
Summary: Blazingly fast append to xlsx file
Keywords: excel,xlsx,rust,append
Author-email: Mihail Boreyko <krakotay@yandex.ru>
Requires-Python: >=3.10
Project-URL: Homepage, https://github.com/krakotay/excelsior
Project-URL: Issues, https://github.com/krakotay/excelsior/issues
